{
	"id" : [
		761156425
	],
	"name" : [
		"Laika Believes: The Sun at Night (Canceled)"
	],
	"blurb" : [
		"Immersive 2D action platformer for PC/Mac/Linux (console later) depicting an alternate history of Laika, the Soviet space dog."
	],
	"goal" : [
		1e+05
	],
	"pledged" : [
		12082
	],
	"state" : [
		"canceled"
	],
	"slug" : [
		"laika-believes-the-sun-at-night"
	],
	"disable_communication" : [
		false
	],
	"country" : [
		"US"
	],
	"currency" : [
		"USD"
	],
	"currency_symbol" : [
		"$"
	],
	"currency_trailing_code" : [
		true
	],
	"deadline" : [
		1376059549
	],
	"state_changed_at" : [
		1375458472
	],
	"created_at" : [
		1332267707
	],
	"launched_at" : [
		1373467549
	],
	"backers_count" : [
		165
	],
	"photo" : {
		"full" : [
			"https://s3.amazonaws.com/ksr/projects/108884/photo-full.jpg?1397775190"
		],
		"ed" : [
			"https://s3.amazonaws.com/ksr/projects/108884/photo-ed.jpg?1397775190"
		],
		"med" : [
			"https://s3.amazonaws.com/ksr/projects/108884/photo-med.jpg?1397775190"
		],
		"little" : [
			"https://s3.amazonaws.com/ksr/projects/108884/photo-little.jpg?1397775190"
		],
		"small" : [
			"https://s3.amazonaws.com/ksr/projects/108884/photo-small.jpg?1397775190"
		],
		"thumb" : [
			"https://s3.amazonaws.com/ksr/projects/108884/photo-thumb.jpg?1397775190"
		],
		"1024x768" : [
			"https://s3.amazonaws.com/ksr/projects/108884/photo-1024x768.jpg?1397775190"
		],
		"1536x1152" : [
			"https://s3.amazonaws.com/ksr/projects/108884/photo-1536x1152.jpg?1397775190"
		]
	},
	"creator" : {
		"id" : [
			1483335373
		],
		"name" : [
			"John Warren"
		],
		"slug" : [
			"johnewarren"
		],
		"avatar" : {
			"thumb" : [
				"https://s3.amazonaws.com/ksr/avatars/1024940/fb_profile_picture.thumb.jpg?1337825813"
			],
			"small" : [
				"https://s3.amazonaws.com/ksr/avatars/1024940/fb_profile_picture.small.jpg?1337825813"
			],
			"medium" : [
				"https://s3.amazonaws.com/ksr/avatars/1024940/fb_profile_picture.medium.jpg?1337825813"
			]
		},
		"urls" : {
			"web" : {
				"user" : [
					"https://www.kickstarter.com/profile/johnewarren"
				]
			},
			"api" : {
				"user" : [
					"https://api.kickstarter.com/v1/users/1483335373?signature=1399957235.cc4994927bc7228b64783bb3c58e80c242e24744"
				]
			}
		}
	},
	"location" : {
		"id" : [
			2357536
		],
		"name" : [
			"Austin"
		],
		"slug" : [
			"austin-tx"
		],
		"short_name" : [
			"Austin, TX"
		],
		"displayable_name" : [
			"Austin, TX"
		],
		"country" : [
			"US"
		],
		"state" : [
			"TX"
		],
		"urls" : {
			"web" : {
				"discover" : [
					"https://www.kickstarter.com/discover/places/austin-tx"
				],
				"location" : [
					"https://www.kickstarter.com/locations/austin-tx"
				]
			},
			"api" : {
				"nearby_projects" : [
					"https://api.kickstarter.com/v1/discover?signature=1399951821.40b481f638520857e1b4ca887f5449fda5c8328f&amp;woe_id=2357536"
				]
			}
		}
	},
	"category" : {
		"id" : [
			35
		],
		"name" : [
			"Video Games"
		],
		"slug" : [
			"games/video games"
		],
		"position" : [
			7
		],
		"parent_id" : [
			12
		],
		"urls" : {
			"web" : {
				"discover" : [
					"http://www.kickstarter.com/discover/categories/games/video%20games"
				]
			}
		}
	},
	"urls" : {
		"web" : {
			"project" : [
				"https://www.kickstarter.com/projects/johnewarren/laika-believes-the-sun-at-night"
			],
			"project_short" : [
				"http://kck.st/1749vQR"
			],
			"updates" : [
				"https://www.kickstarter.com/projects/johnewarren/laika-believes-the-sun-at-night/posts"
			]
		},
		"api" : {
			"project" : [
				"https://api.kickstarter.com/v1/projects/761156425?signature=1399957235.4be66fc010f46405b823da0cc923727275c3deb5"
			],
			"comments" : [
				"https://api.kickstarter.com/v1/projects/761156425/comments?signature=1399957235.ada8d044c5d4ce50c64c79b6f6ef34ad72656f06"
			],
			"updates" : [
				"https://api.kickstarter.com/v1/projects/761156425/updates?signature=1399957235.ac044417961dd005e34da2e0ee5582bff0c40cb5"
			]
		}
	},
	"updated_at" : [
		1397775195
	],
	"canceled_at" : [
		1375458472
	],
	"video" : {
		"id" : [
			259514
		],
		"status" : [
			"successful"
		],
		"high" : [
			"https://d2pq0u4uni88oo.cloudfront.net/projects/108884/video-259514-h264_high.mp4?2013"
		],
		"base" : [
			"https://d2pq0u4uni88oo.cloudfront.net/projects/108884/video-259514-h264_base.mp4?2013"
		],
		"webm" : [
			"https://d2pq0u4uni88oo.cloudfront.net/projects/108884/video-259514-webm.webm?2013"
		],
		"width" : [
			640
		],
		"height" : [
			360
		],
		"frame" : [
			"https://d2pq0u4uni88oo.cloudfront.net/projects/108884/video-259514-h264_base.jpg?2013"
		]
	},
	"comments_count" : [
		6
	],
	"updates_count" : [
		12
	],
	"rewards" : [
		{
			"id" : 0,
			"minimum" : 1,
			"reward" : "No Reward"
		},
		{
			"id" : 1763498,
			"minimum" : 1,
			"reward" : "Give us a a dollar! You&#39;ll get access to backer-only updates and Laika Believes digital wallpaper.",
			"shipping_applicable" : true,
			"shipping" : "domestic",
			"shipping_amount" : "0.0",
			"estimated_delivery_on" : 1377993600,
			"project_id" : 761156425,
			"backers_count" : 5,
			"updated_at" : 1373698019
		},
		{
			"id" : 1798837,
			"minimum" : 1,
			"reward" : "Give us your non-US money too! You&#39;ll get access to backer-only updates and a Laika Believes digital wallpaper.",
			"shipping_applicable" : false,
			"estimated_delivery_on" : 1377993600,
			"project_id" : 761156425,
			"backers_count" : 3,
			"updated_at" : 1374235496
		},
		{
			"id" : 894708,
			"minimum" : 10,
			"reward" : "Early Bird Special! Digital Copy of Laika Believes: The Sun at Night.",
			"shipping_applicable" : false,
			"estimated_delivery_on" : 1377993600,
			"project_id" : 761156425,
			"backers_count" : 88,
			"updated_at" : 1375454460,
			"limit" : 500,
			"remaining" : 412
		},
		{
			"id" : 1698481,
			"minimum" : 15,
			"reward" : "Digital Copy of Laika Believes: The Sun at Night.",
			"shipping_applicable" : false,
			"estimated_delivery_on" : 1377993600,
			"project_id" : 761156425,
			"backers_count" : 6,
			"updated_at" : 1375439031
		},
		{
			"id" : 1698482,
			"minimum" : 25,
			"reward" : "Digital Copy of Laika Believes: The Sun at Night, Digital Copy of the Official Game Soundtrack.",
			"shipping_applicable" : false,
			"estimated_delivery_on" : 1377993600,
			"project_id" : 761156425,
			"backers_count" : 10,
			"updated_at" : 1374462127
		},
		{
			"id" : 1698483,
			"minimum" : 40,
			"reward" : "All of the above plus Pre-Sale of the next two installments of Laika Believes.",
			"shipping_applicable" : false,
			"estimated_delivery_on" : 1377993600,
			"project_id" : 761156425,
			"backers_count" : 16,
			"updated_at" : 1375458231
		},
		{
			"id" : 1698484,
			"minimum" : 50,
			"reward" : "All of the above, plus a physical copy of Laika Believes: The Sun at Night.",
			"shipping_applicable" : true,
			"shipping" : "domestic",
			"shipping_amount" : "0.0",
			"estimated_delivery_on" : 1380585600,
			"project_id" : 761156425,
			"backers_count" : 7,
			"updated_at" : 1374986916
		},
		{
			"id" : 1698485,
			"minimum" : 60,
			"reward" : "All of the above, plus a digital copy of the Laika Believes: The Sun at Night Art Book.",
			"shipping_applicable" : true,
			"shipping" : "domestic",
			"shipping_amount" : "0.0",
			"estimated_delivery_on" : 1380585600,
			"project_id" : 761156425,
			"backers_count" : 5,
			"updated_at" : 1375215557
		},
		{
			"id" : 1698486,
			"minimum" : 80,
			"reward" : "All of the above, plus a limited run, silk screen version of our Laika Believes poster.",
			"shipping_applicable" : true,
			"shipping" : "domestic",
			"shipping_amount" : "0.0",
			"estimated_delivery_on" : 1380585600,
			"project_id" : 761156425,
			"backers_count" : 3,
			"updated_at" : 1373494010
		},
		{
			"id" : 1698487,
			"minimum" : 100,
			"reward" : "All of the above, plus Alpha access to Laika Believes: The Sun at Night. Help us finalize the game with your feedback!",
			"shipping_applicable" : true,
			"shipping" : "domestic",
			"shipping_amount" : "0.0",
			"estimated_delivery_on" : 1380585600,
			"project_id" : 761156425,
			"backers_count" : 8,
			"updated_at" : 1375413272
		},
		{
			"id" : 1698488,
			"minimum" : 120,
			"reward" : "All of the above, plus a physical copy of The Logbook; a compilation of diary entries, log book excerpts, experimental analysis, and more details from Laika&#39;s world that will flesh out more of her universe and offer more depth to her story.",
			"shipping_applicable" : true,
			"shipping" : "domestic",
			"shipping_amount" : "0.0",
			"estimated_delivery_on" : 1380585600,
			"project_id" : 761156425,
			"backers_count" : 0,
			"updated_at" : 1371160262
		},
		{
			"id" : 1698489,
			"minimum" : 150,
			"reward" : "All of the above, plus your choice of ONE of the following Bundles:\\r\\n\\r\\nArt Bundle: Physical copy of the art book, framed digital print of a piece of concept art, button set. \\r\\n\\r\\nSound Bundle: Physical copy of the official soundtrack including bonus remixes by assorted chiptunes artists, chiptunes inspired Laika sticker.\\r\\n\\r\\nPet Lover&#39;s Bundle: Laika Believes frisbee, I Believe in Laika bandana, dog treats - All for your pooch!",
			"shipping_applicable" : true,
			"shipping" : "domestic",
			"shipping_amount" : "0.0",
			"estimated_delivery_on" : 1380585600,
			"project_id" : 761156425,
			"backers_count" : 3,
			"updated_at" : 1374069033
		},
		{
			"id" : 1698490,
			"minimum" : 175,
			"reward" : "All of the rewards from the first nine tiers, your choice of ONE of the above bundles, plus a Laika Believes Plush",
			"shipping_applicable" : true,
			"shipping" : "domestic",
			"shipping_amount" : "0.0",
			"estimated_delivery_on" : 1380585600,
			"project_id" : 761156425,
			"backers_count" : 3,
			"updated_at" : 1373794829
		},
		{
			"id" : 1698491,
			"minimum" : 275,
			"reward" : "All of the rewards from the first nine tiers, plus your choice of TWO of the above bundles",
			"shipping_applicable" : true,
			"shipping" : "domestic",
			"shipping_amount" : "0.0",
			"estimated_delivery_on" : 1380585600,
			"project_id" : 761156425,
			"backers_count" : 0,
			"updated_at" : 1370370210
		},
		{
			"id" : 1698492,
			"minimum" : 300,
			"reward" : "All of the rewards from the first nine tiers, your choice of TWO of the above bundles, plus a Laika Believes Plush",
			"shipping_applicable" : true,
			"shipping" : "domestic",
			"shipping_amount" : "0.0",
			"estimated_delivery_on" : 1380585600,
			"project_id" : 761156425,
			"backers_count" : 2,
			"updated_at" : 1374064756
		},
		{
			"id" : 1698493,
			"minimum" : 425,
			"reward" : "All of the rewards from the first nine tiers, plus ALL THREE of the above bundles.",
			"shipping_applicable" : true,
			"shipping" : "domestic",
			"shipping_amount" : "0.0",
			"estimated_delivery_on" : 1380585600,
			"project_id" : 761156425,
			"backers_count" : 0,
			"updated_at" : 1370370210
		},
		{
			"id" : 1698494,
			"minimum" : 450,
			"reward" : "All of the rewards from the first nine tiers, ALL THREE of the above bundles, plus a Laika Believes Plush",
			"shipping_applicable" : true,
			"shipping" : "domestic",
			"shipping_amount" : "0.0",
			"estimated_delivery_on" : 1380585600,
			"project_id" : 761156425,
			"backers_count" : 0,
			"updated_at" : 1370370210
		},
		{
			"id" : 1698495,
			"minimum" : 700,
			"reward" : "All of the above, plus custom Laika Converse Shoes. Just tell us your shoe size and wait for your hand painted, Laika themed kicks to arrive!",
			"shipping_applicable" : true,
			"shipping" : "domestic",
			"shipping_amount" : "0.0",
			"estimated_delivery_on" : 1383264000,
			"project_id" : 761156425,
			"backers_count" : 1,
			"updated_at" : 1373574850
		},
		{
			"id" : 1698496,
			"minimum" : 1000,
			"reward" : "All of the above, plus your name listed in the credits at the end of the game.",
			"shipping_applicable" : true,
			"shipping" : "domestic",
			"shipping_amount" : "0.0",
			"estimated_delivery_on" : 1383264000,
			"project_id" : 761156425,
			"backers_count" : 1,
			"updated_at" : 1373565694
		},
		{
			"id" : 1698497,
			"minimum" : 2500,
			"reward" : "All of the above, plus a custom piece of artwork made special just for you by one of our awesome art team members. Do you want to see your pet - dog, cat, bird, lizard, etc - stylized as Laika, spacesuit and all? Now you can!",
			"shipping_applicable" : true,
			"shipping" : "domestic",
			"shipping_amount" : "0.0",
			"estimated_delivery_on" : 1383264000,
			"project_id" : 761156425,
			"backers_count" : 0,
			"updated_at" : 1370369935
		},
		{
			"id" : 1698498,
			"minimum" : 5000,
			"reward" : "All of the above, plus a custom in game Laika skin. Work with our art team to turn your lovable pup into a playable cyborg warrior! \\r\\n\\r\\n(For technical reasons, your custom character needs to the same size/shape as Laika, but we will customize to resemble your dog as much as possible.)",
			"shipping_applicable" : true,
			"shipping" : "domestic",
			"shipping_amount" : "0.0",
			"estimated_delivery_on" : 1383264000,
			"project_id" : 761156425,
			"backers_count" : 1,
			"updated_at" : 1374093141,
			"limit" : 5,
			"remaining" : 4
		},
		{
			"id" : 1698499,
			"minimum" : 10000,
			"reward" : "All of the above, plus Executive Producer credit for Laika Believes: The Sun at Night.",
			"shipping_applicable" : true,
			"shipping" : "domestic",
			"shipping_amount" : "0.0",
			"estimated_delivery_on" : 1383264000,
			"project_id" : 761156425,
			"backers_count" : 0,
			"updated_at" : 1370369935,
			"limit" : 5,
			"remaining" : 5
		}
	]
}