{
	"id" : [
		1300744771
	],
	"name" : [
		"Pangenic"
	],
	"blurb" : [
		"A Steampunk inspired turn-based tactics game featuring Victorian scientists battling disease with blades and guns."
	],
	"goal" : [
		45000
	],
	"pledged" : [
		12583.74
	],
	"state" : [
		"failed"
	],
	"slug" : [
		"pangenic"
	],
	"disable_communication" : [
		false
	],
	"country" : [
		"US"
	],
	"currency" : [
		"USD"
	],
	"currency_symbol" : [
		"$"
	],
	"currency_trailing_code" : [
		true
	],
	"deadline" : [
		1349472780
	],
	"state_changed_at" : [
		1349472782
	],
	"created_at" : [
		1341895135
	],
	"launched_at" : [
		1347259187
	],
	"backers_count" : [
		410
	],
	"photo" : {
		"full" : [
			"https://s3.amazonaws.com/ksr/projects/249747/photo-full.jpg?1397789236"
		],
		"ed" : [
			"https://s3.amazonaws.com/ksr/projects/249747/photo-ed.jpg?1397789236"
		],
		"med" : [
			"https://s3.amazonaws.com/ksr/projects/249747/photo-med.jpg?1397789236"
		],
		"little" : [
			"https://s3.amazonaws.com/ksr/projects/249747/photo-little.jpg?1397789236"
		],
		"small" : [
			"https://s3.amazonaws.com/ksr/projects/249747/photo-small.jpg?1397789236"
		],
		"thumb" : [
			"https://s3.amazonaws.com/ksr/projects/249747/photo-thumb.jpg?1397789236"
		],
		"1024x768" : [
			"https://s3.amazonaws.com/ksr/projects/249747/photo-1024x768.jpg?1397789236"
		],
		"1536x1152" : [
			"https://s3.amazonaws.com/ksr/projects/249747/photo-1536x1152.jpg?1397789236"
		]
	},
	"creator" : {
		"id" : [
			2138288614
		],
		"name" : [
			"The Dada Factory"
		],
		"slug" : [
			"dada"
		],
		"avatar" : {
			"thumb" : [
				"https://s3.amazonaws.com/ksr/avatars/3315242/dadaBannerV03.thumb.jpg?1344299067"
			],
			"small" : [
				"https://s3.amazonaws.com/ksr/avatars/3315242/dadaBannerV03.small.jpg?1344299067"
			],
			"medium" : [
				"https://s3.amazonaws.com/ksr/avatars/3315242/dadaBannerV03.medium.jpg?1344299067"
			]
		},
		"urls" : {
			"web" : {
				"user" : [
					"https://www.kickstarter.com/profile/dada"
				]
			},
			"api" : {
				"user" : [
					"https://api.kickstarter.com/v1/users/2138288614?signature=1399951322.418014b4adc471ef5d8d7cb934ac322b9ab7fcdc"
				]
			}
		}
	},
	"location" : {
		"id" : [
			2487610
		],
		"name" : [
			"Salt Lake City"
		],
		"slug" : [
			"salt-lake-city-ut"
		],
		"short_name" : [
			"Salt Lake City, UT"
		],
		"displayable_name" : [
			"Salt Lake City, UT"
		],
		"country" : [
			"US"
		],
		"state" : [
			"UT"
		],
		"urls" : {
			"web" : {
				"discover" : [
					"https://www.kickstarter.com/discover/places/salt-lake-city-ut"
				],
				"location" : [
					"https://www.kickstarter.com/locations/salt-lake-city-ut"
				]
			},
			"api" : {
				"nearby_projects" : [
					"https://api.kickstarter.com/v1/discover?signature=1399908621.1573d74b6b28dbb7fc893ee6914b53ea49bf967e&amp;woe_id=2487610"
				]
			}
		}
	},
	"category" : {
		"id" : [
			35
		],
		"name" : [
			"Video Games"
		],
		"slug" : [
			"games/video games"
		],
		"position" : [
			7
		],
		"parent_id" : [
			12
		],
		"urls" : {
			"web" : {
				"discover" : [
					"http://www.kickstarter.com/discover/categories/games/video%20games"
				]
			}
		}
	},
	"urls" : {
		"web" : {
			"project" : [
				"https://www.kickstarter.com/projects/dada/pangenic"
			],
			"project_short" : [
				"http://kck.st/U41IKN"
			],
			"updates" : [
				"https://www.kickstarter.com/projects/dada/pangenic/posts"
			]
		},
		"api" : {
			"project" : [
				"https://api.kickstarter.com/v1/projects/1300744771?signature=1399951322.9b65f661bb6b7bf7dc953ecf132ee2753788ffed"
			],
			"comments" : [
				"https://api.kickstarter.com/v1/projects/1300744771/comments?signature=1399951322.7c0200fadc0859151f5da746cd4434801dbc550f"
			],
			"updates" : [
				"https://api.kickstarter.com/v1/projects/1300744771/updates?signature=1399951322.9481b48c110b6c09a5c795ad52afbe5e4219c5a6"
			]
		}
	},
	"updated_at" : [
		1397789241
	],
	"failed_at" : [
		1349472782
	],
	"video" : {
		"id" : [
			156472
		],
		"status" : [
			"successful"
		],
		"high" : [
			"https://d2pq0u4uni88oo.cloudfront.net/projects/249747/video-156472-h264_high.mp4?2012"
		],
		"base" : [
			"https://d2pq0u4uni88oo.cloudfront.net/projects/249747/video-156472-h264_base.mp4?2012"
		],
		"width" : [
			640
		],
		"height" : [
			360
		],
		"frame" : [
			"https://d2pq0u4uni88oo.cloudfront.net/projects/249747/video-156472-h264_base.jpg?2012"
		]
	},
	"comments_count" : [
		28
	],
	"updates_count" : [
		4
	],
	"rewards" : [
		{
			"id" : 0,
			"minimum" : 1,
			"reward" : "No Reward"
		},
		{
			"id" : 941906,
			"minimum" : 3,
			"reward" : "JEAN-BAPTISTE LAMARCK: Thank you and Kickstarter Digital Wallpaper.",
			"shipping_applicable" : false,
			"estimated_delivery_on" : 1385856000,
			"project_id" : 1300744771,
			"backers_count" : 6,
			"updated_at" : 1348515943
		},
		{
			"id" : 940794,
			"minimum" : 15,
			"reward" : "FRANCIS GALTON: Digital copy of PANGENIC for PC +  An exclusive In-Game Equipment Pack to help kickstart your war on the epidemic + Previous Reward.",
			"shipping_applicable" : false,
			"estimated_delivery_on" : 1385856000,
			"project_id" : 1300744771,
			"backers_count" : 235,
			"updated_at" : 1349451233
		},
		{
			"id" : 941863,
			"minimum" : 25,
			"reward" : "MARIE CURIE: All Previous Rewards + Keep involved in the development process with access to our Internal Development Blog + Pangenic Digital Soundtrack.",
			"shipping_applicable" : false,
			"estimated_delivery_on" : 1385856000,
			"project_id" : 1300744771,
			"backers_count" : 39,
			"updated_at" : 1349462008
		},
		{
			"id" : 941904,
			"minimum" : 42,
			"reward" : "NIKOLA TESLA: All Previous Rewards + Kickstarter Exclusive In-Game Scientist Bernhardt Jameson, utilizing the unique Mechanical Computation Tech-Tree.",
			"shipping_applicable" : false,
			"estimated_delivery_on" : 1385856000,
			"project_id" : 1300744771,
			"backers_count" : 78,
			"updated_at" : 1349466007
		},
		{
			"id" : 941905,
			"minimum" : 58,
			"reward" : "GREGOR MENDEL: All Previous Rewards + Pangenic Infected Creature Research Poster (please add $10 for international shipping) + Your name featured in the production credits.",
			"shipping_applicable" : false,
			"estimated_delivery_on" : 1385856000,
			"project_id" : 1300744771,
			"backers_count" : 16,
			"updated_at" : 1349413353
		},
		{
			"id" : 941975,
			"minimum" : 84,
			"reward" : "ADA LOVELACE: All Previous Rewards + Become a Pangenic Science Advisor: Cast your vote on design decisions, give us feedback in first-round beta testing and enter to have a Pangenic scientist named after you!",
			"shipping_applicable" : false,
			"estimated_delivery_on" : 1385856000,
			"project_id" : 1300744771,
			"backers_count" : 12,
			"updated_at" : 1349469997
		},
		{
			"id" : 960120,
			"minimum" : 150,
			"reward" : "LOUIS PASTEUR: All Previous Rewards + Original late-Victorian or Edwardian novel (featured in the background of the video) with personally inscribed Thank You note (please add $15 for international shipping).",
			"shipping_applicable" : false,
			"estimated_delivery_on" : 1385856000,
			"project_id" : 1300744771,
			"backers_count" : 4,
			"updated_at" : 1349186685,
			"limit" : 30,
			"remaining" : 26
		},
		{
			"id" : 960101,
			"minimum" : 225,
			"reward" : "MICHAEL FARADAY: All Previous Rewards + The official Pangenic Field Guide featuring the story, scientists and monsters from Pangenic (please add $15 for international shipping).",
			"shipping_applicable" : false,
			"estimated_delivery_on" : 1385856000,
			"project_id" : 1300744771,
			"backers_count" : 1,
			"updated_at" : 1348117449,
			"limit" : 15,
			"remaining" : 14
		},
		{
			"id" : 960112,
			"minimum" : 600,
			"reward" : "CHARLES DARWIN: All Previous Rewards + A hand-inked portrait of you, or person of your choosing, rendered in the style of the Pangenic scientists. Printed on canvas and mounted in a vintage wooden frame (please add $25 for international shipping).",
			"shipping_applicable" : false,
			"estimated_delivery_on" : 1385856000,
			"project_id" : 1300744771,
			"backers_count" : 3,
			"updated_at" : 1349248843,
			"limit" : 15,
			"remaining" : 12
		},
		{
			"id" : 1035748,
			"minimum" : 3500,
			"reward" : "ALBERT EINSTEIN: All Previous Rewards + 5 Day all expenses paid trip (from anywhere in the continental US) for the official Pangenic launch party at The Leonardo Museum in downtown Salt Lake City.",
			"shipping_applicable" : false,
			"estimated_delivery_on" : 1385856000,
			"project_id" : 1300744771,
			"backers_count" : 0,
			"updated_at" : 1347259065,
			"limit" : 3,
			"remaining" : 3
		}
	]
}