{
	"id" : [
		1336566180
	],
	"name" : [
		"Ground Pounders"
	],
	"blurb" : [
		"A hex-based sci-fi strategy game featuring the tanks, air craft and infantry of the Sword of the Stars universe."
	],
	"goal" : [
		42000
	],
	"pledged" : [
		21414
	],
	"state" : [
		"failed"
	],
	"slug" : [
		"ground-pounders"
	],
	"disable_communication" : [
		false
	],
	"country" : [
		"US"
	],
	"currency" : [
		"USD"
	],
	"currency_symbol" : [
		"$"
	],
	"currency_trailing_code" : [
		true
	],
	"deadline" : [
		1380393353
	],
	"state_changed_at" : [
		1380393354
	],
	"created_at" : [
		1374870747
	],
	"launched_at" : [
		1377801353
	],
	"backers_count" : [
		410
	],
	"photo" : {
		"full" : [
			"https://s3.amazonaws.com/ksr/projects/630340/photo-full.jpg?1397828622"
		],
		"ed" : [
			"https://s3.amazonaws.com/ksr/projects/630340/photo-ed.jpg?1397828622"
		],
		"med" : [
			"https://s3.amazonaws.com/ksr/projects/630340/photo-med.jpg?1397828622"
		],
		"little" : [
			"https://s3.amazonaws.com/ksr/projects/630340/photo-little.jpg?1397828622"
		],
		"small" : [
			"https://s3.amazonaws.com/ksr/projects/630340/photo-small.jpg?1397828622"
		],
		"thumb" : [
			"https://s3.amazonaws.com/ksr/projects/630340/photo-thumb.jpg?1397828622"
		],
		"1024x768" : [
			"https://s3.amazonaws.com/ksr/projects/630340/photo-1024x768.jpg?1397828622"
		],
		"1536x1152" : [
			"https://s3.amazonaws.com/ksr/projects/630340/photo-1536x1152.jpg?1397828622"
		]
	},
	"creator" : {
		"id" : [
			60954475
		],
		"name" : [
			"Kerberos Productions"
		],
		"slug" : [
			"kerberosproductions"
		],
		"avatar" : {
			"thumb" : [
				"https://s3.amazonaws.com/ksr/avatars/7444897/kerb_logo_bitmap.thumb.jpg?1374870215"
			],
			"small" : [
				"https://s3.amazonaws.com/ksr/avatars/7444897/kerb_logo_bitmap.small.jpg?1374870215"
			],
			"medium" : [
				"https://s3.amazonaws.com/ksr/avatars/7444897/kerb_logo_bitmap.medium.jpg?1374870215"
			]
		},
		"urls" : {
			"web" : {
				"user" : [
					"https://www.kickstarter.com/profile/kerberosproductions"
				]
			},
			"api" : {
				"user" : [
					"https://api.kickstarter.com/v1/users/60954475?signature=1399954069.2ca3f06c50e0923d863d9843da296a20cd33c195"
				]
			}
		}
	},
	"location" : {
		"id" : [
			9807
		],
		"name" : [
			"Vancouver"
		],
		"slug" : [
			"vancouver-ca"
		],
		"short_name" : [
			"Vancouver, Canada"
		],
		"displayable_name" : [
			"Vancouver, Canada"
		],
		"country" : [
			"CA"
		],
		"state" : [
			"BC"
		],
		"urls" : {
			"web" : {
				"discover" : [
					"https://www.kickstarter.com/discover/places/vancouver-ca"
				],
				"location" : [
					"https://www.kickstarter.com/locations/vancouver-ca"
				]
			},
			"api" : {
				"nearby_projects" : [
					"https://api.kickstarter.com/v1/discover?signature=1399951821.17edcd5cba492b1f5025d67c37acaf63f635bcd5&amp;woe_id=9807"
				]
			}
		}
	},
	"category" : {
		"id" : [
			35
		],
		"name" : [
			"Video Games"
		],
		"slug" : [
			"games/video games"
		],
		"position" : [
			7
		],
		"parent_id" : [
			12
		],
		"urls" : {
			"web" : {
				"discover" : [
					"http://www.kickstarter.com/discover/categories/games/video%20games"
				]
			}
		}
	},
	"urls" : {
		"web" : {
			"project" : [
				"https://www.kickstarter.com/projects/kerberosproductions/ground-pounders"
			],
			"project_short" : [
				"http://kck.st/1ckRPUh"
			],
			"updates" : [
				"https://www.kickstarter.com/projects/kerberosproductions/ground-pounders/posts"
			]
		},
		"api" : {
			"project" : [
				"https://api.kickstarter.com/v1/projects/1336566180?signature=1399954069.0576f282b3227efbd3c70b47c3eac1935b3daeba"
			],
			"comments" : [
				"https://api.kickstarter.com/v1/projects/1336566180/comments?signature=1399954069.4e90cd2b45e96fecd3e173622da18eff404d4041"
			],
			"updates" : [
				"https://api.kickstarter.com/v1/projects/1336566180/updates?signature=1399954069.f365f2967706f994e9db00e9469782cd428a3419"
			]
		}
	},
	"updated_at" : [
		1397828630
	],
	"failed_at" : [
		1380393354
	],
	"video" : {
		"id" : [
			288113
		],
		"status" : [
			"successful"
		],
		"high" : [
			"https://d2pq0u4uni88oo.cloudfront.net/projects/630340/video-288113-h264_high.mp4?2013"
		],
		"base" : [
			"https://d2pq0u4uni88oo.cloudfront.net/projects/630340/video-288113-h264_base.mp4?2013"
		],
		"webm" : [
			"https://d2pq0u4uni88oo.cloudfront.net/projects/630340/video-288113-webm.webm?2013"
		],
		"width" : [
			640
		],
		"height" : [
			360
		],
		"frame" : [
			"https://d2pq0u4uni88oo.cloudfront.net/projects/630340/video-288113-h264_base.jpg?2013"
		]
	},
	"comments_count" : [
		104
	],
	"updates_count" : [
		29
	],
	"rewards" : [
		{
			"id" : 0,
			"minimum" : 1,
			"reward" : "No Reward"
		},
		{
			"id" : 1923910,
			"minimum" : 5,
			"reward" : "Thank you for your support! Every supporter at this level and above will receive access to the password-protected Backers Only forums for Ground Pounders, campaign updates, and access to Backers Only wallpapers and art.",
			"shipping_applicable" : false,
			"estimated_delivery_on" : 1377993600,
			"project_id" : 1336566180,
			"backers_count" : 6,
			"updated_at" : 1380351900
		},
		{
			"id" : 1923911,
			"minimum" : 15,
			"reward" : "EARLY BIRD PRICE! Early supporters of our campaign can grab their download copy of Ground Pounders upon release at a special price. Thank you for your support!",
			"shipping_applicable" : false,
			"estimated_delivery_on" : 1385856000,
			"project_id" : 1336566180,
			"backers_count" : 211,
			"updated_at" : 1380385940,
			"limit" : 1000,
			"remaining" : 789
		},
		{
			"id" : 1923912,
			"minimum" : 20,
			"reward" : "LISTING IN GAME CREDITS. All Supporters at this level and above will be able to download a copy of the game upon release and will have the option of being listed officially in the game&#39;s credits.",
			"shipping_applicable" : false,
			"estimated_delivery_on" : 1385856000,
			"project_id" : 1336566180,
			"backers_count" : 30,
			"updated_at" : 1380387233
		},
		{
			"id" : 1924133,
			"minimum" : 25,
			"reward" : "BUDDY PACK! Download TWO copies of Ground Pounders for one low price on release! Instant multi-player fun for you and a lucky friend. Plus a listing in the game&#39;s credits, and access to the Backer&#39;s Only forum!",
			"shipping_applicable" : false,
			"estimated_delivery_on" : 1385856000,
			"project_id" : 1336566180,
			"backers_count" : 37,
			"updated_at" : 1380288201
		},
		{
			"id" : 1924134,
			"minimum" : 30,
			"reward" : "DIGITAL BUNDLE. You will get a download copy of Ground Pounders on release day, listing in the game&#39;s credits, plus a Digital Bundle of Wallpapers and art.",
			"shipping_applicable" : false,
			"estimated_delivery_on" : 1385856000,
			"project_id" : 1336566180,
			"backers_count" : 18,
			"updated_at" : 1380289268
		},
		{
			"id" : 1924135,
			"minimum" : 45,
			"reward" : "BETA ACCESS. Supporters at this level and above will get immediate access to the Backers-Only Beta of the game beginning in October 2013 and access to the closed Backers-Only Beta forum, in addition to the Digital Bundle, listing in the game&#39;s Credits, and a downloadable copy of the game upon release.",
			"shipping_applicable" : false,
			"estimated_delivery_on" : 1380585600,
			"project_id" : 1336566180,
			"backers_count" : 30,
			"updated_at" : 1380376608
		},
		{
			"id" : 1969558,
			"minimum" : 50,
			"reward" : "Beta Plus Dice! Backers at this level and above will receive a complimentary set of special decorative Sword of the Stars dice! Each set contains six beautiful six-sided dice, with emblems representing the six major empires of the Sword of the Stars universe in the years 2408-2508.",
			"shipping_applicable" : true,
			"estimated_delivery_on" : 1385856000,
			"project_id" : 1336566180,
			"backers_count" : 13,
			"updated_at" : 1380349538,
			"shipping" : "international",
			"shipping_amount" : "10.0"
		},
		{
			"id" : 1924136,
			"minimum" : 75,
			"reward" : "CHALLENGE COIN. Supporters at this level will receive Beta Access plus the official Ground Pounders Challenge Coin! This beautiful collectible coin is a replica of the Sol Force challenge coins which are issued to survivors of each successful Ground Forces campaign.",
			"shipping_applicable" : true,
			"estimated_delivery_on" : 1385856000,
			"project_id" : 1336566180,
			"backers_count" : 5,
			"updated_at" : 1380237302,
			"shipping" : "international",
			"shipping_amount" : "10.0"
		},
		{
			"id" : 1969667,
			"minimum" : 125,
			"reward" : "The Sword of the Stars Premium Lore Book! One of the most popular reward levels for a previous campaign was the MONSTER Premium Lore Book. This limited edition hardback is a compendium of over 300 pages of art and fiction for the Sotsverse, including tons of never-released concept art and team interviews with the creators of the Sword of the Stars franchise from 2004-2013. Personally signed by the creators!",
			"shipping_applicable" : true,
			"estimated_delivery_on" : 1385856000,
			"project_id" : 1336566180,
			"backers_count" : 7,
			"updated_at" : 1380152914,
			"shipping" : "international",
			"shipping_amount" : "15.0"
		},
		{
			"id" : 1924205,
			"minimum" : 125,
			"reward" : "STICK PACK.Supporters at this level will receive Beta Acess, the official Challenge Coin, and a Special Edition 16-gigabyte USB drive, which will arrive with the contents of your Digital Bundle loaded onto it, as well as a few extra surprise goodies from the team at Kerberos Productions.",
			"shipping_applicable" : true,
			"estimated_delivery_on" : 1385856000,
			"project_id" : 1336566180,
			"backers_count" : 19,
			"updated_at" : 1380289301,
			"shipping" : "international",
			"shipping_amount" : "15.0"
		},
		{
			"id" : 1984417,
			"minimum" : 150,
			"reward" : "COMBO PACK. This reward level includes Beta Access, the Premium Lore Book, the physical items of the Stick Pack, and our SotS Dice.",
			"shipping_applicable" : true,
			"estimated_delivery_on" : 1385856000,
			"project_id" : 1336566180,
			"backers_count" : 10,
			"updated_at" : 1380345187,
			"shipping" : "international",
			"shipping_amount" : "20.0"
		},
		{
			"id" : 1924206,
			"minimum" : 175,
			"reward" : "GAMBLER&#39;S PACK. Supporters at this level will receive Beta Access, the official Challenge Coin, the Special Edition 16GB USB drive, a printed deck of Ground Pounders Playing Cards, and a set of collectible Sol Force dog tags!",
			"shipping_applicable" : true,
			"estimated_delivery_on" : 1385856000,
			"project_id" : 1336566180,
			"backers_count" : 4,
			"updated_at" : 1380325550,
			"shipping" : "international",
			"shipping_amount" : "15.0"
		},
		{
			"id" : 1924211,
			"minimum" : 250,
			"reward" : "BARRACK&#39;S PACK. Supporters at this level will receive Beta Access, the official Challenge Coin, the Special Edition 16GB USB drive, TWO printed decks of Ground Pounders Playing Cards, a set of Sol Force dog-tags, a Ground Forces t-shirt, AND an official replica of the stainless steel Hydration Bottle carried by Ground Forces soldiers in the field!",
			"shipping_applicable" : true,
			"estimated_delivery_on" : 1385856000,
			"project_id" : 1336566180,
			"backers_count" : 13,
			"updated_at" : 1380231744,
			"shipping" : "international",
			"shipping_amount" : "25.0"
		},
		{
			"id" : 1924237,
			"minimum" : 350,
			"reward" : "DESIGN A CARD! Supporters at this level will be able to Design a Unique Combat Card to be added to the final game! Work with the Design Team for Ground Pounders and receive professional design credit for your contribution. This reward comes with the Beta Access package and the Physical Items of the Barracks Pack. (PLEASE NOTE: Kerberos Productions reserves the right to veto any Card Design which violates its policies on hate speech, harassment, or age-inappropriate content.)",
			"shipping_applicable" : true,
			"estimated_delivery_on" : 1385856000,
			"project_id" : 1336566180,
			"backers_count" : 0,
			"updated_at" : 1379451255,
			"limit" : 10,
			"remaining" : 10,
			"shipping" : "international",
			"shipping_amount" : "25.0"
		},
		{
			"id" : 1924238,
			"minimum" : 450,
			"reward" : "DESIGN A UNIT!  Backers at this level will be able to Design a Unique Combat Unit to be added to the final game! Work with the Design Team for Ground Pounders and receive professional credit for your contribution. This reward comes with the Beta Access package, but no physical perks. If you wish to add the items from the Barracks Pack, Gambler&#39;s Pack, Stick Pack or Challenge Coin at this level, please add the price of the Pack to your Pledge. (PLEASE NOTE: Kerberos Productions reserves the right to veto any Unit Design which violates its policies on hate speech, harassment, or age-inappropriate content.)",
			"shipping_applicable" : false,
			"estimated_delivery_on" : 1385856000,
			"project_id" : 1336566180,
			"backers_count" : 1,
			"updated_at" : 1379633531,
			"limit" : 5,
			"remaining" : 4
		},
		{
			"id" : 1924239,
			"minimum" : 650,
			"reward" : "DESIGN A BATTLE! Pick your favorite historical battle and work with the Ground Pounders design team to create a canonical planetary battle of the Hiver War era!  Receive professional credit for your contribution to the game and to the Sword of the Stars universe. This reward comes with the Beta Access package and all of the Physical Perks for the campaign, including the Barrack&#39;s Pack and copy of the Lore Book. (PLEASE NOTE: Kerberos Productions reserves the right to veto any Card Battle Design which violates its policies on hate speech, harassment, or age-inappropriate content.)",
			"shipping_applicable" : true,
			"estimated_delivery_on" : 1385856000,
			"project_id" : 1336566180,
			"backers_count" : 1,
			"updated_at" : 1380032991,
			"limit" : 5,
			"remaining" : 4,
			"shipping" : "international",
			"shipping_amount" : "25.0"
		},
		{
			"id" : 1924244,
			"minimum" : 1000,
			"reward" : "TRUE BELIEVER. Backers at this level will receive TWO Ground Forces t-shirts and a special VIP card, personalized with your name. \\r\\nHolders of the Kerberos VIP card will be granted insider-only access to games in development and free entry to any Kerberos public event, including those that would normally be Press Only. They will also have the right to cast a vote when choosing the company&#39;s next project. (PLEASE NOTE: This reward comes with no additional physical perks. If you wish to add the items from the Barracks Pack, Gambler&#39;s Pack, Stick Pack or Challenge Coin at this level, please add the price of the Pack and any additional Shipping to your Pledge.)",
			"shipping_applicable" : false,
			"estimated_delivery_on" : 1385856000,
			"project_id" : 1336566180,
			"backers_count" : 3,
			"updated_at" : 1378251311,
			"limit" : 15,
			"remaining" : 12
		},
		{
			"id" : 2001043,
			"minimum" : 10000,
			"reward" : "THE OUYA LEVEL! Just in case someone wants to OUYA us! :) We hear there&#39;s a lot of that going around! Is OUYA a verb?",
			"shipping_applicable" : false,
			"estimated_delivery_on" : 1385856000,
			"project_id" : 1336566180,
			"backers_count" : 0,
			"updated_at" : 1379983262,
			"limit" : 3,
			"remaining" : 3
		}
	]
}