{
	"id" : [
		1304249523
	],
	"name" : [
		"Yogventures!"
	],
	"blurb" : [
		"Yogventures! is an open world sandbox adventure game featuring characters developed by Simon and Lewis of The Yogscast!"
	],
	"goal" : [
		250000
	],
	"pledged" : [
		567665.08
	],
	"state" : [
		"successful"
	],
	"slug" : [
		"yogventures"
	],
	"disable_communication" : [
		false
	],
	"country" : [
		"US"
	],
	"currency" : [
		"USD"
	],
	"currency_symbol" : [
		"$"
	],
	"currency_trailing_code" : [
		true
	],
	"deadline" : [
		1336332209
	],
	"state_changed_at" : [
		1336332209
	],
	"created_at" : [
		1333297010
	],
	"launched_at" : [
		1333740209
	],
	"backers_count" : [
		13647
	],
	"photo" : {
		"full" : [
			"https://s3.amazonaws.com/ksr/projects/121782/photo-full.jpg?1397776550"
		],
		"ed" : [
			"https://s3.amazonaws.com/ksr/projects/121782/photo-ed.jpg?1397776550"
		],
		"med" : [
			"https://s3.amazonaws.com/ksr/projects/121782/photo-med.jpg?1397776550"
		],
		"little" : [
			"https://s3.amazonaws.com/ksr/projects/121782/photo-little.jpg?1397776550"
		],
		"small" : [
			"https://s3.amazonaws.com/ksr/projects/121782/photo-small.jpg?1397776550"
		],
		"thumb" : [
			"https://s3.amazonaws.com/ksr/projects/121782/photo-thumb.jpg?1397776550"
		],
		"1024x768" : [
			"https://s3.amazonaws.com/ksr/projects/121782/photo-1024x768.jpg?1397776550"
		],
		"1536x1152" : [
			"https://s3.amazonaws.com/ksr/projects/121782/photo-1536x1152.jpg?1397776550"
		]
	},
	"creator" : {
		"id" : [
			1709604221
		],
		"name" : [
			"Winterkewl Games LLC"
		],
		"slug" : [
			"winterkewlgames"
		],
		"avatar" : {
			"thumb" : [
				"https://s3.amazonaws.com/ksr/avatars/1028112/meHiRes.thumb.jpg?1343760998"
			],
			"small" : [
				"https://s3.amazonaws.com/ksr/avatars/1028112/meHiRes.small.jpg?1343760998"
			],
			"medium" : [
				"https://s3.amazonaws.com/ksr/avatars/1028112/meHiRes.medium.jpg?1343760998"
			]
		},
		"urls" : {
			"web" : {
				"user" : [
					"https://www.kickstarter.com/profile/winterkewlgames"
				]
			},
			"api" : {
				"user" : [
					"https://api.kickstarter.com/v1/users/1709604221?signature=1399955906.e01b010302ab38a045feaf631681958201bf3b98"
				]
			}
		}
	},
	"location" : {
		"id" : [
			2442047
		],
		"name" : [
			"Los Angeles"
		],
		"slug" : [
			"los-angeles-ca"
		],
		"short_name" : [
			"Los Angeles, CA"
		],
		"displayable_name" : [
			"Los Angeles, CA"
		],
		"country" : [
			"US"
		],
		"state" : [
			"CA"
		],
		"urls" : {
			"web" : {
				"discover" : [
					"https://www.kickstarter.com/discover/places/los-angeles-ca"
				],
				"location" : [
					"https://www.kickstarter.com/locations/los-angeles-ca"
				]
			},
			"api" : {
				"nearby_projects" : [
					"https://api.kickstarter.com/v1/discover?signature=1399951818.e609e9257aa2bbc4a05b2f5e5d3584cce5ac138e&amp;woe_id=2442047"
				]
			}
		}
	},
	"category" : {
		"id" : [
			35
		],
		"name" : [
			"Video Games"
		],
		"slug" : [
			"games/video games"
		],
		"position" : [
			7
		],
		"parent_id" : [
			12
		],
		"urls" : {
			"web" : {
				"discover" : [
					"http://www.kickstarter.com/discover/categories/games/video%20games"
				]
			}
		}
	},
	"urls" : {
		"web" : {
			"project" : [
				"https://www.kickstarter.com/projects/winterkewlgames/yogventures"
			],
			"project_short" : [
				"http://kck.st/Hmlz7V"
			],
			"updates" : [
				"https://www.kickstarter.com/projects/winterkewlgames/yogventures/posts"
			]
		},
		"api" : {
			"project" : [
				"https://api.kickstarter.com/v1/projects/1304249523?signature=1399955906.827ee049f3a88d6a732119b687ae517eae77830b"
			],
			"comments" : [
				"https://api.kickstarter.com/v1/projects/1304249523/comments?signature=1399955906.f53c563ff0b73a9a3d7a1c88d919817e1995f3e1"
			],
			"updates" : [
				"https://api.kickstarter.com/v1/projects/1304249523/updates?signature=1399955906.47df1ee128396d1409885c1a72fe8f5482f87ac9"
			]
		}
	},
	"updated_at" : [
		1398667094
	],
	"successful_at" : [
		1336332209
	],
	"potd_at" : [
		1335139200
	],
	"ksr_blurb" : [
		"&lt;p&gt;Taking the idea of \"build your own adventure\" to the extreme,&lt;i&gt;Yogventures\\u00a0&lt;/i&gt;will let you create fantastical new worlds to share and play with your friends. The only rules are the ones you make up, so you can explore, dig, build, or \\u2014 why not? \\u2014 blow it all up!\\u00a0&lt;/p&gt;"
	],
	"video" : {
		"id" : [
			95295
		],
		"status" : [
			"successful"
		],
		"high" : [
			"https://d2pq0u4uni88oo.cloudfront.net/projects/121782/video-95295-h264_high.mp4?2012"
		],
		"base" : [
			"https://d2pq0u4uni88oo.cloudfront.net/projects/121782/video-95295-h264_base.mp4?2012"
		],
		"width" : [
			560
		],
		"height" : [
			314
		],
		"frame" : [
			"https://d2pq0u4uni88oo.cloudfront.net/projects/121782/video-95295-h264_base.jpg?2012"
		]
	},
	"comments_count" : [
		7844
	],
	"updates_count" : [
		25
	],
	"rewards" : [
		{
			"id" : 0,
			"minimum" : 1,
			"reward" : "No Reward"
		},
		{
			"id" : 568381,
			"minimum" : 15,
			"reward" : "A full copy of Yogventures on PC and Mac! You will also get access to the game during the closed BETA at the end of the year. This low price is only available to those who have kickstarted Yogventures!",
			"shipping_applicable" : false,
			"estimated_delivery_on" : 1354320000,
			"project_id" : 1304249523,
			"backers_count" : 7069,
			"updated_at" : 1399700711
		},
		{
			"id" : 568382,
			"minimum" : 25,
			"reward" : "All previous + You will receive ALPHA access, a full month before the closed beta! You&#39;ll also receive exclusive registration to the development forum - where YOUR input will shape the direction and features added to the game.",
			"shipping_applicable" : false,
			"estimated_delivery_on" : 1351728000,
			"project_id" : 1304249523,
			"backers_count" : 3404,
			"updated_at" : 1398799686
		},
		{
			"id" : 639018,
			"minimum" : 30,
			"reward" : "2 full copies of Yogventures on PC and Mac! One for you and one for a friend! You and your friend will also get access to the game during the closed BETA at the end of the year. This low price is only available to those who have kickstarted Yogventures!",
			"shipping_applicable" : false,
			"estimated_delivery_on" : 1354320000,
			"project_id" : 1304249523,
			"backers_count" : 759,
			"updated_at" : 1398249652
		},
		{
			"id" : 568383,
			"minimum" : 60,
			"reward" : "All previous + VIP access to a special \"founders\" area on the development forums + Access to PRE-ALPHA development builds TWO whole months before the beta + We&#39;ll send you a beautiful POSTER featuring digital art from the game similar to the images seen here! Designed exclusively for the kickstarter campaign by our extremely talented concept artists!",
			"shipping_applicable" : false,
			"estimated_delivery_on" : 1349049600,
			"project_id" : 1304249523,
			"backers_count" : 966,
			"updated_at" : 1399580326
		},
		{
			"id" : 568384,
			"minimum" : 90,
			"reward" : "All previous + You&#39;ll get a special T-shirt designed exclusively by the Yogventures concept artists! (available in a range of sizes/colours) + Your name will be added to the game&#39;s credits!",
			"shipping_applicable" : false,
			"estimated_delivery_on" : 1354320000,
			"project_id" : 1304249523,
			"backers_count" : 980,
			"updated_at" : 1395805148,
			"limit" : 2500,
			"remaining" : 1520
		},
		{
			"id" : 576553,
			"minimum" : 200,
			"reward" : "All previous + You&#39;ll receive an awesome high quality print of concept art from the game SIGNED by Simon and Lewis as a thank you for your support!",
			"shipping_applicable" : false,
			"estimated_delivery_on" : 1354320000,
			"project_id" : 1304249523,
			"backers_count" : 93,
			"updated_at" : 1397916105,
			"limit" : 1000,
			"remaining" : 907
		},
		{
			"id" : 568385,
			"minimum" : 300,
			"reward" : "All previous + You&#39;ll receive a limited edition \"Deluxe Collector&#39;s Edition\" featuring a whole bunch of amazing stuff - including the following: Yogventures on DVD, Soundtrack CD, Yogventures comic book, Yogventures themed playing cards, Honeydew plushie and much much more!",
			"shipping_applicable" : false,
			"estimated_delivery_on" : 1354320000,
			"project_id" : 1304249523,
			"backers_count" : 120,
			"updated_at" : 1336937566,
			"limit" : 1000,
			"remaining" : 880
		},
		{
			"id" : 576954,
			"minimum" : 500,
			"reward" : "All previous + A numbered and limited edition high quality collectible painted statuette of Honeydew and Xephos looking totally badass! Also you will get the opportunity to name a  special weapon, NPC or location in Yogventures! It could be you who forges &#39;Dave!&#39;s Axe of Axing&#39; (+12 to Axes) for all other players to wield in their Yogventure!",
			"shipping_applicable" : false,
			"estimated_delivery_on" : 1354320000,
			"project_id" : 1304249523,
			"backers_count" : 37,
			"updated_at" : 1343115728,
			"limit" : 500,
			"remaining" : 463
		},
		{
			"id" : 568387,
			"minimum" : 750,
			"reward" : "All previous + Sponsor and choose a block or creature to be added to the game! We will contact you and work with you to add a custom block, apparatus, decoration, creature, NPC, weapon or other item of your choice into the game! You will be thanked in the patch notes, development videos and listed in the credits when your request is added!",
			"shipping_applicable" : false,
			"estimated_delivery_on" : 1385856000,
			"project_id" : 1304249523,
			"backers_count" : 36,
			"updated_at" : 1336937521,
			"limit" : 250,
			"remaining" : 214
		},
		{
			"id" : 568388,
			"minimum" : 2000,
			"reward" : "All previous + a personalized \"thank you\" video will be made specifically for YOU by Lewis and Simon with some exclusive behind-the-scenes content and posted unlisted on YouTube then e-mailed to you! (so you can choose to share it or not)",
			"shipping_applicable" : false,
			"estimated_delivery_on" : 1354320000,
			"project_id" : 1304249523,
			"backers_count" : 1,
			"updated_at" : 1336334480,
			"limit" : 50,
			"remaining" : 49
		},
		{
			"id" : 568389,
			"minimum" : 5000,
			"reward" : "All previous + your Minecraft character gets to become a character in Shadow of Israphel!\\r\\n\\r\\nWe&#39;ll invite you to join us while we film an episode of Shadow of Israphel and you will play a part in the adventure! Will you aid our heroes or seek to hinder their adventure? The choice is yours!",
			"shipping_applicable" : false,
			"estimated_delivery_on" : 1354320000,
			"project_id" : 1304249523,
			"backers_count" : 5,
			"updated_at" : 1336937524,
			"limit" : 5,
			"remaining" : 0
		},
		{
			"id" : 568390,
			"minimum" : 10000,
			"reward" : "All previous (including walk on role in Shadow of Israphel) + &#39;Have lunch with the Yogscast!&#39; \\r\\nYou and a guest will be invited to join\\r\\nSimon, Lewis and members of the development team to talk about the game, SoI, the finer points of Jaffa Cake consumption and anything/everything else! You will also get the opportunity to pick up some exclusive swag, pose for pictures with the gang (we suggest practicing voguing and your &#39;Blue Steel&#39; look in advance) and have the greatest (lunch)time of your life! \\r\\n\\r\\nThe event can be scheduled either during this year&#39;s E3 in Los Angeles, California or later this year in Bristol, England. You will need to provide your own travel arrangements.",
			"shipping_applicable" : false,
			"estimated_delivery_on" : 1338508800,
			"project_id" : 1304249523,
			"backers_count" : 5,
			"updated_at" : 1336937486,
			"limit" : 5,
			"remaining" : 0
		}
	]
}