{
	"id" : [
		723491702
	],
	"name" : [
		"Dead Crusade (Canceled)"
	],
	"blurb" : [
		"A Medieval Co-Op Horror game powered by Unreal Engine 4, set in real world 14th century Europe during the Black Death pandemic."
	],
	"goal" : [
		250000
	],
	"pledged" : [
		9745
	],
	"state" : [
		"canceled"
	],
	"slug" : [
		"dead-crusade"
	],
	"disable_communication" : [
		false
	],
	"country" : [
		"US"
	],
	"currency" : [
		"USD"
	],
	"currency_symbol" : [
		"$"
	],
	"currency_trailing_code" : [
		true
	],
	"deadline" : [
		1399203171
	],
	"state_changed_at" : [
		1397844316
	],
	"created_at" : [
		1382969617
	],
	"launched_at" : [
		1396611171
	],
	"backers_count" : [
		325
	],
	"photo" : {
		"full" : [
			"https://s3.amazonaws.com/ksr/projects/736942/photo-full.jpg?1397853738"
		],
		"ed" : [
			"https://s3.amazonaws.com/ksr/projects/736942/photo-ed.jpg?1397853738"
		],
		"med" : [
			"https://s3.amazonaws.com/ksr/projects/736942/photo-med.jpg?1397853738"
		],
		"little" : [
			"https://s3.amazonaws.com/ksr/projects/736942/photo-little.jpg?1397853738"
		],
		"small" : [
			"https://s3.amazonaws.com/ksr/projects/736942/photo-small.jpg?1397853738"
		],
		"thumb" : [
			"https://s3.amazonaws.com/ksr/projects/736942/photo-thumb.jpg?1397853738"
		],
		"1024x768" : [
			"https://s3.amazonaws.com/ksr/projects/736942/photo-1024x768.jpg?1397853738"
		],
		"1536x1152" : [
			"https://s3.amazonaws.com/ksr/projects/736942/photo-1536x1152.jpg?1397853738"
		]
	},
	"creator" : {
		"id" : [
			648243123
		],
		"name" : [
			"Aesthetic Games Inc."
		],
		"avatar" : {
			"thumb" : [
				"https://s3.amazonaws.com/ksr/avatars/8521119/Aesthetic_Games_7.thumb.jpg?1391963897"
			],
			"small" : [
				"https://s3.amazonaws.com/ksr/avatars/8521119/Aesthetic_Games_7.small.jpg?1391963897"
			],
			"medium" : [
				"https://s3.amazonaws.com/ksr/avatars/8521119/Aesthetic_Games_7.medium.jpg?1391963897"
			]
		},
		"urls" : {
			"web" : {
				"user" : [
					"https://www.kickstarter.com/profile/648243123"
				]
			},
			"api" : {
				"user" : [
					"https://api.kickstarter.com/v1/users/648243123?signature=1399958248.90e097c52fd13b686b7e8de3c49e59d224d9be7c"
				]
			}
		}
	},
	"location" : {
		"id" : [
			2434976
		],
		"name" : [
			"Lake Jackson"
		],
		"slug" : [
			"lake-jackson-tx"
		],
		"short_name" : [
			"Lake Jackson, TX"
		],
		"displayable_name" : [
			"Lake Jackson, TX"
		],
		"country" : [
			"US"
		],
		"state" : [
			"TX"
		],
		"urls" : {
			"web" : {
				"discover" : [
					"https://www.kickstarter.com/discover/places/lake-jackson-tx"
				],
				"location" : [
					"https://www.kickstarter.com/locations/lake-jackson-tx"
				]
			},
			"api" : {
				"nearby_projects" : [
					"https://api.kickstarter.com/v1/discover?signature=1399956156.8d9069a2e3b8471df6847ba58812a1c07ba7e18d&amp;woe_id=2434976"
				]
			}
		}
	},
	"category" : {
		"id" : [
			35
		],
		"name" : [
			"Video Games"
		],
		"slug" : [
			"games/video games"
		],
		"position" : [
			7
		],
		"parent_id" : [
			12
		],
		"urls" : {
			"web" : {
				"discover" : [
					"http://www.kickstarter.com/discover/categories/games/video%20games"
				]
			}
		}
	},
	"urls" : {
		"web" : {
			"project" : [
				"https://www.kickstarter.com/projects/648243123/dead-crusade"
			],
			"project_short" : [
				"http://kck.st/1hIoS8Y"
			],
			"updates" : [
				"https://www.kickstarter.com/projects/648243123/dead-crusade/posts"
			]
		},
		"api" : {
			"project" : [
				"https://api.kickstarter.com/v1/projects/723491702?signature=1399958248.d997d8504301a53c90c4aab8dbc43e5a3dd3556d"
			],
			"comments" : [
				"https://api.kickstarter.com/v1/projects/723491702/comments?signature=1399958248.1f2b7db24a40255548f0f5b3cefa1dee29c8c58e"
			],
			"updates" : [
				"https://api.kickstarter.com/v1/projects/723491702/updates?signature=1399958248.9e785dd8afcc7017d89935489eb19860c85655d0"
			]
		}
	},
	"updated_at" : [
		1397853762
	],
	"canceled_at" : [
		1397844316
	],
	"video" : {
		"id" : [
			370756
		],
		"status" : [
			"successful"
		],
		"high" : [
			"https://d2pq0u4uni88oo.cloudfront.net/projects/736942/video-370756-h264_high.mp4?2014"
		],
		"base" : [
			"https://d2pq0u4uni88oo.cloudfront.net/projects/736942/video-370756-h264_base.mp4?2014"
		],
		"webm" : [
			"https://d2pq0u4uni88oo.cloudfront.net/projects/736942/video-370756-webm.webm?2014"
		],
		"width" : [
			640
		],
		"height" : [
			360
		],
		"frame" : [
			"https://d2pq0u4uni88oo.cloudfront.net/projects/736942/video-370756-h264_base.jpg?2014"
		]
	},
	"comments_count" : [
		36
	],
	"updates_count" : [
		3
	],
	"rewards" : [
		{
			"id" : 0,
			"minimum" : 1,
			"reward" : "No Reward"
		},
		{
			"id" : 2099104,
			"minimum" : 15,
			"reward" : "AFFLICTED (digital)\\r\\n============================= \\r\\nTHE GAME + INSIDER FORUM + TIER FORUM BADGE\\r\\n============================= \\r\\nEARLY BIRD: Get the $25 reward for only 15$!",
			"limit" : 1500,
			"shipping_applicable" : false,
			"estimated_delivery_on" : 1448928000,
			"project_id" : 723491702,
			"remaining" : 1301,
			"backers_count" : 199,
			"updated_at" : 1397841357
		},
		{
			"id" : 2502221,
			"minimum" : 20,
			"reward" : "AFFLICTED (digital)\\r\\n============================= \\r\\nTHE GAME + INSIDER FORUM + TIER FORUM BADGE\\r\\n============================= \\r\\nINCLUDES ALL PREVIOUS REWARDS\\r\\n\\r\\n\\u25cf This tier includes the DRM-Free digital download of Dead Crusade plus `Insider Forum` access to exclusive developer updates featuring developer videos, first looks at in-game shots, writing from the game, game art, development polls and much more. \\u25cf Forum Badge: Afflicted",
			"shipping_applicable" : false,
			"estimated_delivery_on" : 1448928000,
			"project_id" : 723491702,
			"backers_count" : 10,
			"updated_at" : 1397824202
		},
		{
			"id" : 2515806,
			"minimum" : 30,
			"reward" : "INFECTED (digital) ============================= THE GAME + BETA ACCESS + WALLPAPER PACK + INSIDER FORUM + TIER FORUM BADGE ============================= \\r\\nINCLUDES ALL PREVIOUS REWARDS\\r\\n\\r\\n\\u25cf EARLY BIRD: Get the $35 reward for only 30$!",
			"limit" : 1000,
			"shipping_applicable" : false,
			"estimated_delivery_on" : 1448928000,
			"project_id" : 723491702,
			"remaining" : 973,
			"backers_count" : 27,
			"updated_at" : 1397700843
		},
		{
			"id" : 2502222,
			"minimum" : 35,
			"reward" : "INFECTED (digital)\\r\\n============================= \\r\\nTHE GAME + BETA ACCESS + WALLPAPER PACK + SPECIAL CREDITS + INSIDER FORUM + TIER FORUM BADGE\\r\\n============================= \\r\\nINCLUDES ALL PREVIOUS REWARDS\\r\\n\\r\\n\\u25cf Early access to Beta- Play Dead Crusade months before launch! \\u25cf Receive a Kickstarter Exclusive Wallpaper Pack. \\u25cf Get listed as a `Contributor` in the games credits \\u25cf Forum Badge: Infected",
			"shipping_applicable" : false,
			"estimated_delivery_on" : 1448928000,
			"project_id" : 723491702,
			"backers_count" : 3,
			"updated_at" : 1397141734
		},
		{
			"id" : 2515780,
			"minimum" : 40,
			"reward" : "PLAUGED (digital) ============================= \\r\\nTHE GAME + ALPHA ACCESS + WALLPAPER PACK + SOUNDTRACK + DIGITAL ART BOOK + INSIDER FORUM + TIER FORUM BADGE ============================= INCLUDES ALL PREVIOUS REWARDS \\r\\n\\u25cf EARLY BIRD: Get the $50 reward for only 40$!",
			"limit" : 500,
			"shipping_applicable" : false,
			"estimated_delivery_on" : 1448928000,
			"project_id" : 723491702,
			"remaining" : 450,
			"backers_count" : 50,
			"updated_at" : 1397841857
		},
		{
			"id" : 2502223,
			"minimum" : 50,
			"reward" : "PLAUGED (digital)\\r\\n============================= \\r\\nTHE GAME + ALPHA ACCESS + WALLPAPER PACK + SOUNDTRACK + DIGITAL ART BOOK + INSIDER FORUM + TIER FORUM BADGE \\r\\n=============================\\r\\nINCLUDES ALL PREVIOUS REWARDS \\r\\n\\u25cf Early beta access is not early enough? Alpha access grants even earlier access! You will receive an earlier early access code to get digital downloads of the alpha builds \\u25cf Get the MP3 soundtrack from composer Mitchell Gibbs \\u25cf Digital Art Book containing all of the concept art, character renders, and storyboards used to create Dead Crusade  \\u25cf Forum Badge: Plagued",
			"shipping_applicable" : false,
			"estimated_delivery_on" : 1448928000,
			"project_id" : 723491702,
			"backers_count" : 5,
			"updated_at" : 1397737406
		},
		{
			"id" : 2503031,
			"minimum" : 65,
			"reward" : "INFECTED PACK RAT (digital)\\r\\n============================= TWO GAME COPIES + TWO BETA KEYS + WALLPAPER PACK + INSIDER FORUM TIER + FORUM BADGE\\r\\n=============================\\r\\nINCLUDES ALL PREVIOUS REWARDS\\r\\n\\r\\n\\u25cf Recieve two DRM-Free digital downloads of Dead Crusade \\u25cf Give an extra beta key to a friend and play Co-op months before launch\\r\\n \\u25cf Forum Badge: Infected Pack Rat",
			"shipping_applicable" : false,
			"estimated_delivery_on" : 1448928000,
			"project_id" : 723491702,
			"backers_count" : 6,
			"updated_at" : 1397782369
		},
		{
			"id" : 2503032,
			"minimum" : 75,
			"reward" : "PLAGUED PACK RAT (digital) ============================= \\r\\nTWO GAME COPIES + TWO ALPHA KEYS + WALLPAPER PACK + INSIDER FORUM + TIER FORUM BADGE\\r\\n============================= INCLUDES ALL PREVIOUS REWARDS\\r\\n\\r\\n\\u25cf Recieve two DRM-Free digital downloads of Dead Crusade  \\u25cf  Early beta access is not early enough? Alpha access grants even earlier access! You will receive two early Alpha access code to get digital downloads of the alpha builds \\u25cf Forum Badge: Plauged Pack Rat",
			"shipping_applicable" : false,
			"estimated_delivery_on" : 1448928000,
			"project_id" : 723491702,
			"backers_count" : 7,
			"updated_at" : 1397801438
		},
		{
			"id" : 2512967,
			"minimum" : 150,
			"reward" : "DECAYED (Collector&#39;s Edition)\\r\\n=============================\\r\\nBOXED GAME + 4 DIGITAL VERSIONS + LIMITED EDITION 11\" x 17\" POSTER + T-SHIRT + CD SOUNDTRACK + CLOTH MAP + WALLPAPER PACK + SPECIAL CREDITS + INSIDER FORUM + TIER FORUM BADGE\\r\\n=============================\\r\\nINCLUDES ALL PREVIOUS REWARDS\\r\\n\\r\\n\\u25cf Receive an exclusive Dead Crusade special boxed edition containing the game for Windows. The boxed version will be available only through this Kickstarter campaign \\u25cf 4 digital versions of Dead Crusade \\u25cf Exclusive 11\" x 17\" Poster \\u25cf Get an exclusive, limited edition  Dead Crusade T-shirt \\u25cf  CD Soundtrack by composer Mitchell Gibbs \\u25cf Limited Edition detailed cloth map \\u25cf Get listed as a `Executive Backer` in the games credits \\u25cf Forum Badge: Decayed",
			"limit" : 500,
			"shipping_applicable" : true,
			"estimated_delivery_on" : 1448928000,
			"project_id" : 723491702,
			"remaining" : 493,
			"backers_count" : 7,
			"updated_at" : 1397837513,
			"shipping" : "international",
			"shipping_amount" : "15.0"
		},
		{
			"id" : 2515981,
			"minimum" : 300,
			"reward" : "DEFILED (Collector&#39;s Edition)\\r\\n=============================\\r\\nBOXED GAME + 4 DIGITAL VERSIONS +  ART BOOK + LIMITED EDITION 18\" x 24\" POSTER + T-SHIRT + CD SOUNDTRACK  + CLOTH MAP + WALLPAPER PACK + SPECIAL CREDITS + INSIDER FORUM + TIER FORUM BADGE\\r\\n============================= \\r\\n INCLUDES ALL PREVIOUS REWARDS \\u25cf Receive an exclusive Dead Crusade special boxed edition containing the game for Windows. The boxed version will be available only through this Kickstarter campaign \\u25cf 4 digital versions of Dead Crusade .\\u25cf Art Book containing all of the concept art, character renders, and storyboards used to create Dead Crusade \\u25cf Exclusive 18\" x 24\" Poster \\u25cf Get an exclusive, limited edition  Dead Crusade T-shirt \\u25cf  CD Soundtrack by composer Mitchell Gibbs \\u25cf Limited Edition detailed cloth map \\u25cf Get listed as a `Executive Backer` in the games credits \\u25cf Forum Badge: Defiled",
			"limit" : 500,
			"shipping_applicable" : true,
			"estimated_delivery_on" : 1448928000,
			"project_id" : 723491702,
			"remaining" : 500,
			"backers_count" : 0,
			"updated_at" : 1396732866,
			"shipping" : "international",
			"shipping_amount" : "15.0"
		},
		{
			"id" : 2516148,
			"minimum" : 650,
			"reward" : "UNDERTAKER\\r\\n============================= \\r\\nDEATH NOTE + SPECIAL CREDITS + TIER FORUM BADGE\\r\\n============================= \\r\\nINCLUDES ALL PREVIOUS REWARDS \\r\\n\\r\\n\\u25cf  Have your name and a fun personal R.I.P inscription written on Gravestone Relics spread through out the game world. When discovered, your name and personal inscription will be displayed on screen, and players will receive an experience or health bonus! Some restrictions apply. \\u25cf Get listed as a `Executive Benefactor` in the games credits \\u25cf Forum Badge: Undertaker",
			"limit" : 65,
			"shipping_applicable" : false,
			"estimated_delivery_on" : 1448928000,
			"project_id" : 723491702,
			"remaining" : 65,
			"backers_count" : 0,
			"updated_at" : 1396677317
		},
		{
			"id" : 2516184,
			"minimum" : 1200,
			"reward" : "BLACKSMITH\\r\\n============================= \\r\\nFORGED STEEL SWORD  + RAMPANT LION BANNER +  IN-GAME ITEMS + TIER FORUM BADGE \\r\\n============================= INCLUDES ALL PREVIOUS REWARDS\\r\\n\\r\\nYour very own real-life, authentic hand-forged steel sword with custom Dead Crusade engraving and a personalized inscription- Complete with a intricate scabbard to sheath the sword! \\u25cf Also receive a historical 48\" Rampant Lion Banner made of durable cotton that include a wooden hanging rod for easy wall mounting (your choice of 2 colors) \\u25cf Be the envy of all players! We will be giving each class a Kickstarter exclusive in-game head item that gives players a unique look. The Plague Doctor will recieve a Brim Hat, the Soldier a Horned Helm, the Executioner a Studded Half Mask, and the Skirmisher a Nottingham Chaperon. \\u25cf Forum Badge: Blacksmith",
			"limit" : 25,
			"shipping_applicable" : true,
			"estimated_delivery_on" : 1404172800,
			"project_id" : 723491702,
			"remaining" : 24,
			"backers_count" : 1,
			"updated_at" : 1396757127,
			"shipping" : "international",
			"shipping_amount" : "15.0"
		},
		{
			"id" : 2516295,
			"minimum" : 5000,
			"reward" : "MASTER FLESH EATER\\r\\n============================= \\r\\nBECOME A ZOMBIE PACKAGE + SPECIAL CREDITS + TIER FORUM BADGE ============================= INCLUDES ALL PREVIOUS REWARDS \\r\\n\\r\\n\\u25cf Our artists will intricately design and sculpt your face and head in 3D and turn you into a zombie (male or female) for actual in-game use. We will work with you through the development process, as we turn you from a beautiful human into a decayed flesh eating member of the horde \\u25cf  We will also create a 3D Printed Statue of the final result and send it to you, as well as create a special in game Wallpaper, an exclusive 18\" x 24\" Poster of your character likeness rendered inside Unreal Engine 4, and even a special in-game video of your zombie self as a thank you! Shipping is on us. Must supply high res pictures of yourself (or a loved one) for our artists to reference \\u25cf Get listed as a `Special Guest Developer` in the games credits \\u25cf Forum Badge: Master Flesh Eater",
			"limit" : 6,
			"shipping_applicable" : false,
			"estimated_delivery_on" : 1412121600,
			"project_id" : 723491702,
			"remaining" : 6,
			"backers_count" : 0,
			"updated_at" : 1396610115
		},
		{
			"id" : 2516302,
			"minimum" : 10000,
			"reward" : "ASSISTANT DESIGNER\\r\\n============================= \\r\\nBECOME A HERO PACKAGE + TEAM MEETING + SPECIAL CREDITS + TIER FORUM BADGE ============================= INCLUDES ALL PREVIOUS REWARDS \\r\\n\\r\\n\\u25cf Become part of the world of Dead Crusade! We&#39;ll design a Hero NPC and scripted encounter with your input and likeness. We will work closely with you to intricately design and sculpt your face in 3D and add it to a NPC hero character of your choosing. You can be the leader of a travelling caravan under attack by the plagued, a Priest with an attitude who gives players a hard time, or whatever you want (within reason)! \\u25cf We will work with you on both the mission design as well as your heroes role and dialogue. We will have all of your written lines delivered by a professional voice actor! \\u25cf  You will also receive a 3D Printed Statue of your hero character in an action pose of your choice, an exclusive 18\" x 24\" Poster of your in-game character rendered inside Unreal Engine 4, and even a special in-game video of your hero self as a thank you! Shipping is on us. Must supply high res pictures of yourself (or a loved one) for our artists to reference \\u25cf Join an official team meeting through Skype where you can listen in as we collaborate and discuss progress of the game \\u25cf Get listed as a `Assistant Designer` in the games credits \\u25cf Forum Badge: Assistant Designer",
			"limit" : 3,
			"shipping_applicable" : false,
			"estimated_delivery_on" : 1412121600,
			"project_id" : 723491702,
			"remaining" : 3,
			"backers_count" : 0,
			"updated_at" : 1396609997
		}
	]
}