{
	"id" : [
		245655048
	],
	"name" : [
		"A 3D Biology Video Game for the Kinect"
	],
	"blurb" : [
		"We&#39;re making a game using the Kinect to immerse high school students in the amazing cellular world! (You don&#39;t need a Kinect to play)"
	],
	"goal" : [
		27500
	],
	"pledged" : [
		10016
	],
	"state" : [
		"failed"
	],
	"slug" : [
		"a-3d-biology-video-game-for-the-kinect"
	],
	"disable_communication" : [
		false
	],
	"country" : [
		"US"
	],
	"currency" : [
		"USD"
	],
	"currency_symbol" : [
		"$"
	],
	"currency_trailing_code" : [
		true
	],
	"deadline" : [
		1338425261
	],
	"state_changed_at" : [
		1338425262
	],
	"created_at" : [
		1333131326
	],
	"launched_at" : [
		1335833261
	],
	"backers_count" : [
		281
	],
	"photo" : {
		"full" : [
			"https://s3.amazonaws.com/ksr/projects/120187/photo-full.jpg?1397776379"
		],
		"ed" : [
			"https://s3.amazonaws.com/ksr/projects/120187/photo-ed.jpg?1397776379"
		],
		"med" : [
			"https://s3.amazonaws.com/ksr/projects/120187/photo-med.jpg?1397776379"
		],
		"little" : [
			"https://s3.amazonaws.com/ksr/projects/120187/photo-little.jpg?1397776379"
		],
		"small" : [
			"https://s3.amazonaws.com/ksr/projects/120187/photo-small.jpg?1397776379"
		],
		"thumb" : [
			"https://s3.amazonaws.com/ksr/projects/120187/photo-thumb.jpg?1397776379"
		],
		"1024x768" : [
			"https://s3.amazonaws.com/ksr/projects/120187/photo-1024x768.jpg?1397776379"
		],
		"1536x1152" : [
			"https://s3.amazonaws.com/ksr/projects/120187/photo-1536x1152.jpg?1397776379"
		]
	},
	"creator" : {
		"id" : [
			739831580
		],
		"name" : [
			"Blair, Laura Lynn, &amp; Rachel"
		],
		"avatar" : {
			"thumb" : [
				"https://s3.amazonaws.com/ksr/avatars/2348986/about.thumb.jpg?1335311110"
			],
			"small" : [
				"https://s3.amazonaws.com/ksr/avatars/2348986/about.small.jpg?1335311110"
			],
			"medium" : [
				"https://s3.amazonaws.com/ksr/avatars/2348986/about.medium.jpg?1335311110"
			]
		},
		"urls" : {
			"web" : {
				"user" : [
					"https://www.kickstarter.com/profile/739831580"
				]
			},
			"api" : {
				"user" : [
					"https://api.kickstarter.com/v1/users/739831580?signature=1399961864.6a69ca56cc2863f8c10ce890844e2e10406736d7"
				]
			}
		}
	},
	"location" : {
		"id" : [
			2490383
		],
		"name" : [
			"Seattle"
		],
		"slug" : [
			"seattle-wa"
		],
		"short_name" : [
			"Seattle, WA"
		],
		"displayable_name" : [
			"Seattle, WA"
		],
		"country" : [
			"US"
		],
		"state" : [
			"WA"
		],
		"urls" : {
			"web" : {
				"discover" : [
					"https://www.kickstarter.com/discover/places/seattle-wa"
				],
				"location" : [
					"https://www.kickstarter.com/locations/seattle-wa"
				]
			},
			"api" : {
				"nearby_projects" : [
					"https://api.kickstarter.com/v1/discover?signature=1399951821.195076c84f9e27cd1d7979916c7ba772fe796e9c&amp;woe_id=2490383"
				]
			}
		}
	},
	"category" : {
		"id" : [
			35
		],
		"name" : [
			"Video Games"
		],
		"slug" : [
			"games/video games"
		],
		"position" : [
			7
		],
		"parent_id" : [
			12
		],
		"urls" : {
			"web" : {
				"discover" : [
					"http://www.kickstarter.com/discover/categories/games/video%20games"
				]
			}
		}
	},
	"urls" : {
		"web" : {
			"project" : [
				"https://www.kickstarter.com/projects/739831580/a-3d-biology-video-game-for-the-kinect"
			],
			"project_short" : [
				"http://kck.st/Jmhg6B"
			],
			"updates" : [
				"https://www.kickstarter.com/projects/739831580/a-3d-biology-video-game-for-the-kinect/posts"
			]
		},
		"api" : {
			"project" : [
				"https://api.kickstarter.com/v1/projects/245655048?signature=1399961864.d23f0a3d9e797a2d7b3cfc2e8fc2f1d5853c7506"
			],
			"comments" : [
				"https://api.kickstarter.com/v1/projects/245655048/comments?signature=1399961864.db672048dacf757426c96eb57094cd787772c16c"
			],
			"updates" : [
				"https://api.kickstarter.com/v1/projects/245655048/updates?signature=1399961864.fa8dee7126d737837d7c250e588d352753330592"
			]
		}
	},
	"updated_at" : [
		1397776382
	],
	"failed_at" : [
		1338425262
	],
	"video" : {
		"id" : [
			102052
		],
		"status" : [
			"successful"
		],
		"high" : [
			"https://d2pq0u4uni88oo.cloudfront.net/projects/120187/video-102052-h264_high.mp4?2012"
		],
		"base" : [
			"https://d2pq0u4uni88oo.cloudfront.net/projects/120187/video-102052-h264_base.mp4?2012"
		],
		"width" : [
			560
		],
		"height" : [
			314
		],
		"frame" : [
			"https://d2pq0u4uni88oo.cloudfront.net/projects/120187/video-102052-h264_base.jpg?2012"
		]
	},
	"comments_count" : [
		20
	],
	"updates_count" : [
		5
	],
	"rewards" : [
		{
			"id" : 0,
			"minimum" : 1,
			"reward" : "No Reward"
		},
		{
			"id" : 564461,
			"minimum" : 1,
			"reward" : "Your name listed in the credits of the game and on its website. Thank you mucho!!",
			"shipping_applicable" : false,
			"estimated_delivery_on" : 1356998400,
			"project_id" : 245655048,
			"backers_count" : 19,
			"updated_at" : 1338344521
		},
		{
			"id" : 564462,
			"minimum" : 12,
			"reward" : "A copy of the game for PC/Mac (YOU DON&#39;T need a kinect to play, but you should get one because they&#39;re so much fun!) and a chance to preview and give feedback about the game while we build it + all the above",
			"shipping_applicable" : false,
			"estimated_delivery_on" : 1356998400,
			"project_id" : 245655048,
			"backers_count" : 152,
			"updated_at" : 1338425214
		},
		{
			"id" : 636138,
			"minimum" : 25,
			"reward" : "A set of 5 beautiful desktop and mobile wallpapers featuring 3D biology illustrations by the artists + all the above",
			"shipping_applicable" : false,
			"estimated_delivery_on" : 1356998400,
			"project_id" : 245655048,
			"backers_count" : 45,
			"updated_at" : 1338357737
		},
		{
			"id" : 564466,
			"minimum" : 50,
			"reward" : "A for-backers-only digital book (your choice of iPad or web formats) with game art and animations to explain the concepts taught in the game + all the above",
			"shipping_applicable" : false,
			"estimated_delivery_on" : 1356998400,
			"project_id" : 245655048,
			"backers_count" : 32,
			"updated_at" : 1338348097
		},
		{
			"id" : 564485,
			"minimum" : 75,
			"reward" : "An 18\" x 24\" poster of game art + all the above",
			"shipping_applicable" : false,
			"estimated_delivery_on" : 1356998400,
			"project_id" : 245655048,
			"backers_count" : 4,
			"updated_at" : 1338399379
		},
		{
			"id" : 564487,
			"minimum" : 100,
			"reward" : "An \"I love science\" t-shirt designed by the artists (check to the left for the design) + all the above",
			"shipping_applicable" : false,
			"estimated_delivery_on" : 1356998400,
			"project_id" : 245655048,
			"backers_count" : 21,
			"updated_at" : 1338270823
		},
		{
			"id" : 636160,
			"minimum" : 250,
			"reward" : "A custom version of the game with your choice of names and colors of places and objects in the game + all the above",
			"shipping_applicable" : false,
			"estimated_delivery_on" : 1356998400,
			"project_id" : 245655048,
			"backers_count" : 1,
			"updated_at" : 1337122012
		},
		{
			"id" : 564548,
			"minimum" : 1000,
			"reward" : "An original cell biology oil painting by one of the artists + all the above",
			"shipping_applicable" : false,
			"estimated_delivery_on" : 1367366400,
			"project_id" : 245655048,
			"backers_count" : 2,
			"updated_at" : 1337973811,
			"limit" : 10,
			"remaining" : 8
		}
	]
}