{
	"id" : [
		1982976381
	],
	"name" : [
		"Muti (Canceled)"
	],
	"blurb" : [
		"Muti is a first-person horror experience. A terrifying journey into the darkest magics of the dark continent: Africa."
	],
	"goal" : [
		158000
	],
	"pledged" : [
		613
	],
	"state" : [
		"canceled"
	],
	"slug" : [
		"muti-0"
	],
	"disable_communication" : [
		false
	],
	"country" : [
		"GB"
	],
	"currency" : [
		"GBP"
	],
	"currency_symbol" : [
		"\\u00a3"
	],
	"currency_trailing_code" : [
		false
	],
	"deadline" : [
		1366986456
	],
	"state_changed_at" : [
		1366394475
	],
	"created_at" : [
		1362503880
	],
	"launched_at" : [
		1364394456
	],
	"backers_count" : [
		20
	],
	"photo" : {
		"full" : [
			"https://s3.amazonaws.com/ksr/projects/480416/photo-full.jpg?1397812538"
		],
		"ed" : [
			"https://s3.amazonaws.com/ksr/projects/480416/photo-ed.jpg?1397812538"
		],
		"med" : [
			"https://s3.amazonaws.com/ksr/projects/480416/photo-med.jpg?1397812538"
		],
		"little" : [
			"https://s3.amazonaws.com/ksr/projects/480416/photo-little.jpg?1397812538"
		],
		"small" : [
			"https://s3.amazonaws.com/ksr/projects/480416/photo-small.jpg?1397812538"
		],
		"thumb" : [
			"https://s3.amazonaws.com/ksr/projects/480416/photo-thumb.jpg?1397812538"
		],
		"1024x768" : [
			"https://s3.amazonaws.com/ksr/projects/480416/photo-1024x768.jpg?1397812538"
		],
		"1536x1152" : [
			"https://s3.amazonaws.com/ksr/projects/480416/photo-1536x1152.jpg?1397812538"
		]
	},
	"creator" : {
		"id" : [
			139471188
		],
		"name" : [
			"Celestial Games"
		],
		"avatar" : {
			"thumb" : [
				"https://s3.amazonaws.com/ksr/avatars/5729000/Celestial_small_kick_starter.thumb.jpg?1363809519"
			],
			"small" : [
				"https://s3.amazonaws.com/ksr/avatars/5729000/Celestial_small_kick_starter.small.jpg?1363809519"
			],
			"medium" : [
				"https://s3.amazonaws.com/ksr/avatars/5729000/Celestial_small_kick_starter.medium.jpg?1363809519"
			]
		},
		"urls" : {
			"web" : {
				"user" : [
					"https://www.kickstarter.com/profile/139471188"
				]
			},
			"api" : {
				"user" : [
					"https://api.kickstarter.com/v1/users/139471188?signature=1399956943.ee5d4e05fd69fa849ed0a20caf6693c711aa0598"
				]
			}
		}
	},
	"location" : {
		"id" : [
			1582504
		],
		"name" : [
			"Johannesburg"
		],
		"slug" : [
			"johannesburg-johannesburg-gauteng"
		],
		"short_name" : [
			"Johannesburg, South Africa"
		],
		"displayable_name" : [
			"Johannesburg, South Africa"
		],
		"country" : [
			"ZA"
		],
		"state" : [
			"Gauteng"
		],
		"urls" : {
			"web" : {
				"discover" : [
					"https://www.kickstarter.com/discover/places/johannesburg-johannesburg-gauteng"
				],
				"location" : [
					"https://www.kickstarter.com/locations/johannesburg-johannesburg-gauteng"
				]
			},
			"api" : {
				"nearby_projects" : [
					"https://api.kickstarter.com/v1/discover?signature=1399951951.65d47df5aa13f212eed988fa193fc9ffe73814bc&amp;woe_id=1582504"
				]
			}
		}
	},
	"category" : {
		"id" : [
			35
		],
		"name" : [
			"Video Games"
		],
		"slug" : [
			"games/video games"
		],
		"position" : [
			7
		],
		"parent_id" : [
			12
		],
		"urls" : {
			"web" : {
				"discover" : [
					"http://www.kickstarter.com/discover/categories/games/video%20games"
				]
			}
		}
	},
	"urls" : {
		"web" : {
			"project" : [
				"https://www.kickstarter.com/projects/139471188/muti-0"
			],
			"project_short" : [
				"http://kck.st/ZweU0j"
			],
			"updates" : [
				"https://www.kickstarter.com/projects/139471188/muti-0/posts"
			]
		},
		"api" : {
			"project" : [
				"https://api.kickstarter.com/v1/projects/1982976381?signature=1399956943.59f26f4b66312cedf4dfe0aa5dc81a3f163615dd"
			],
			"comments" : [
				"https://api.kickstarter.com/v1/projects/1982976381/comments?signature=1399956943.7aa36cf87f8872663865299f2773990bd963b435"
			],
			"updates" : [
				"https://api.kickstarter.com/v1/projects/1982976381/updates?signature=1399956943.e756cfe7e1ce3f69b59e47e08eb6d9e731e92f91"
			]
		}
	},
	"updated_at" : [
		1397812547
	],
	"canceled_at" : [
		1366394475
	],
	"video" : {
		"id" : [
			229792
		],
		"status" : [
			"successful"
		],
		"high" : [
			"https://d2pq0u4uni88oo.cloudfront.net/projects/480416/video-229792-h264_high.mp4?2013"
		],
		"base" : [
			"https://d2pq0u4uni88oo.cloudfront.net/projects/480416/video-229792-h264_base.mp4?2013"
		],
		"webm" : [
			"https://d2pq0u4uni88oo.cloudfront.net/projects/480416/video-229792-webm.webm?2013"
		],
		"width" : [
			640
		],
		"height" : [
			360
		],
		"frame" : [
			"https://d2pq0u4uni88oo.cloudfront.net/projects/480416/video-229792-h264_base.jpg?2013"
		]
	},
	"comments_count" : [
		12
	],
	"updates_count" : [
		3
	],
	"rewards" : [
		{
			"id" : 0,
			"minimum" : 1,
			"reward" : "No Reward"
		},
		{
			"id" : 1456167,
			"minimum" : 3,
			"reward" : "Fear Edition:\\r\\n\\r\\nOur deepest thanks and 3 of our exclusive Kickstarter high resolution Muti wallpapers.",
			"limit" : 5000,
			"shipping_applicable" : false,
			"estimated_delivery_on" : 1396310400,
			"project_id" : 1982976381,
			"remaining" : 4998,
			"backers_count" : 2,
			"updated_at" : 1366016631
		},
		{
			"id" : 1456168,
			"minimum" : 8,
			"reward" : "Courage Edition:\\r\\n\\r\\nLots of thanks! And 6 Kickstater exclusive high resolution Muti wallpapers.",
			"limit" : 5000,
			"shipping_applicable" : false,
			"estimated_delivery_on" : 1396310400,
			"project_id" : 1982976381,
			"remaining" : 4999,
			"backers_count" : 1,
			"updated_at" : 1364457662
		},
		{
			"id" : 1456169,
			"minimum" : 15,
			"reward" : "Torch Bearer Edition:\\r\\n\\r\\nYou get the Game! \\r\\nReceive digital copy of the game, downloadable on launch, and 6 of our Kickstarter exclusive high resolution Muti wallpapers.",
			"limit" : 2500,
			"shipping_applicable" : false,
			"estimated_delivery_on" : 1396310400,
			"project_id" : 1982976381,
			"remaining" : 2494,
			"backers_count" : 6,
			"updated_at" : 1365351053
		},
		{
			"id" : 1456170,
			"minimum" : 20,
			"reward" : "Art Investigator Edition: \\r\\n\\r\\nReceive digital copy of the game, downloadable on launch, and 6 of our Kickstarter exclusive high resolution Muti wallpapers. Additionally a copy of the exclusive Muti art book in PDF format. You get to know our artists!",
			"limit" : 2500,
			"shipping_applicable" : false,
			"estimated_delivery_on" : 1396310400,
			"project_id" : 1982976381,
			"remaining" : 2500,
			"backers_count" : 0,
			"updated_at" : 1364403879
		},
		{
			"id" : 1456171,
			"minimum" : 20,
			"reward" : "Story Investigator Edition:\\r\\n\\r\\nReceive digital copy of the game, downloadable on launch, and 6 of our Kickstarter exclusive high resolution Muti wallpapers. Additionally receive the Muti Novel with the added bonus of character bios and the inspirations behind the story, in PDF format.",
			"limit" : 2500,
			"shipping_applicable" : false,
			"estimated_delivery_on" : 1396310400,
			"project_id" : 1982976381,
			"remaining" : 2500,
			"backers_count" : 0,
			"updated_at" : 1363809906
		},
		{
			"id" : 1456172,
			"minimum" : 23,
			"reward" : "The Case closed Edition:\\r\\n\\r\\nReceive digital copy of the game, downloadable on launch, and 6 of our Kickstarter exclusive high resolution Muti wallpapers with the added edition of a copy of the exclusive Muti art book in PDF format. You get to know our artists! And receive the Muti Novel with the added bonus of character bios and the inspirations behind the story, in PDF format.",
			"limit" : 2500,
			"shipping_applicable" : false,
			"estimated_delivery_on" : 1396310400,
			"project_id" : 1982976381,
			"remaining" : 2497,
			"backers_count" : 3,
			"updated_at" : 1365234654
		},
		{
			"id" : 1456173,
			"minimum" : 25,
			"reward" : "Believer Edition:\\r\\n\\r\\nReceive everything from the Case closed Edition but with an added second digital copy of the game, downloadable on launch.",
			"limit" : 2500,
			"shipping_applicable" : false,
			"estimated_delivery_on" : 1396310400,
			"project_id" : 1982976381,
			"remaining" : 2498,
			"backers_count" : 2,
			"updated_at" : 1364604196
		},
		{
			"id" : 1456174,
			"minimum" : 30,
			"reward" : "Ritual Edition:\\r\\n\\r\\nGet two physical postcards, sent off after launch and receive the digital copy of the game, downloadable on launch. 6 of our Kickstarter exclusive high resolution Muti wallpapers with the added edition of a copy of the exclusive Muti art book in PDF format. Also receive the Muti Novel with the added bonus of character bios and the inspirations behind the story, in PDF format.",
			"limit" : 2500,
			"shipping_applicable" : false,
			"estimated_delivery_on" : 1396310400,
			"project_id" : 1982976381,
			"remaining" : 2500,
			"backers_count" : 0,
			"updated_at" : 1363809906
		},
		{
			"id" : 1456175,
			"minimum" : 50,
			"reward" : "The Truth -Seeker Edition: \\r\\n\\r\\nThe first tier where you receive the boxed version of the Muti game with the added opportunity to vote for your favorite of the two additional characters you would like to see first as the next character. On top of that get two physical postcards, sent off after launch and receive the digital copy of the game, downloadable on launch. 6 of our Kickstarter exclusive high resolution Muti wallpapers with the added edition of a copy of the exclusive Muti art book in PDF format. Also receive the Muti Novel with the added bonus of character bios and the inspirations behind the story, in PDF format.",
			"limit" : 2500,
			"shipping_applicable" : false,
			"estimated_delivery_on" : 1396310400,
			"project_id" : 1982976381,
			"remaining" : 2496,
			"backers_count" : 4,
			"updated_at" : 1364400718
		},
		{
			"id" : 1456176,
			"minimum" : 90,
			"reward" : "Scarifical Edition:\\r\\n\\r\\nYou get to wear our t-shirt! and show everyone your belief! Receive the digital version of the game, the novel and the art book, with 6 wallpapers, an exclusive Muti t-shirt and the chance to vote for the character you want to see next.",
			"limit" : 2000,
			"shipping_applicable" : false,
			"estimated_delivery_on" : 1396310400,
			"project_id" : 1982976381,
			"remaining" : 1998,
			"backers_count" : 2,
			"updated_at" : 1364415537
		},
		{
			"id" : 1456177,
			"minimum" : 140,
			"reward" : "Tribal Edition:\\r\\n\\r\\nReceive the boxed version of the Muti game with the added opportunity to vote for favorite of the two additional characters you would like to see first as the next character. On top of that get two physical postcards, sent off after launch and receive the digital copy of the game, downloadable on launch, and 6 of our Kickstarter exclusive high resolution Muti wallpapers with the added edition of a copy of the exclusive Muti art book in PDF format. You get to know our artists! And receive the Muti Novel with the added bonus of character bios and the inspirations behind the story, in PDF format. Additionally you get an exclusive Muti t-shirt and the chance to vote for the character you want to see next.",
			"limit" : 1300,
			"shipping_applicable" : false,
			"estimated_delivery_on" : 1396310400,
			"project_id" : 1982976381,
			"remaining" : 1300,
			"backers_count" : 0,
			"updated_at" : 1363874682
		},
		{
			"id" : 1456178,
			"minimum" : 200,
			"reward" : "Bone thrower Edition:\\r\\n\\r\\nPrepare for everything you would receive from the Tribal Edition with an additional digital version of the game and an exclusive Muti physical soft cover novel.",
			"limit" : 700,
			"shipping_applicable" : false,
			"estimated_delivery_on" : 1396310400,
			"project_id" : 1982976381,
			"remaining" : 700,
			"backers_count" : 0,
			"updated_at" : 1363872011
		},
		{
			"id" : 1456179,
			"minimum" : 300,
			"reward" : "Bone Reader Edition:\\r\\n\\r\\nReceive the boxed version of the Muti game with the added opportunity to vote for your favorite which one of the two additional characters you would like to see first as the next character. On top of that get two physical postcards, sent off after launch and receive two digital copies of the game, downloadable on launch, and 6 of our Kickstarter exclusive high resolution Muti wallpapers with the added edition of a copy of the physical exclusive Muti art book. You get to know our artists!",
			"limit" : 350,
			"shipping_applicable" : false,
			"estimated_delivery_on" : 1396310400,
			"project_id" : 1982976381,
			"remaining" : 350,
			"backers_count" : 0,
			"updated_at" : 1363809906
		},
		{
			"id" : 1456180,
			"minimum" : 550,
			"reward" : "Bone collector Edition:\\r\\n\\r\\nPrepare for everything you would receive from the Tribal Edition with an additional digital version of the game the exclusive hard cover Muti art book and soft cover Muti novel.",
			"limit" : 200,
			"shipping_applicable" : false,
			"estimated_delivery_on" : 1396310400,
			"project_id" : 1982976381,
			"remaining" : 200,
			"backers_count" : 0,
			"updated_at" : 1363874828
		},
		{
			"id" : 1456181,
			"minimum" : 600,
			"reward" : "Body Collector Edition:\\r\\n\\r\\nThe Body Collector is the first signed edition reward. Receive everything from the Bone Collector edition with signed copies of the boxed game, the soft cover Muti novel and the hard cover Muti art book and get your name proudly etched into the cold chambers in the morgue or on the walls of our in-game South Africa.",
			"limit" : 100,
			"shipping_applicable" : false,
			"estimated_delivery_on" : 1396310400,
			"project_id" : 1982976381,
			"remaining" : 100,
			"backers_count" : 0,
			"updated_at" : 1363809906
		},
		{
			"id" : 1459231,
			"minimum" : 750,
			"reward" : "Dark Ceremonial Edition:\\r\\n\\r\\nReceive a print of your choice (from the options provided) of one of the exclusively painted artworks from our African artist of scenes from the game as an added bonus to this tier. On top of that receive everything in the Body Collector Edition.",
			"limit" : 50,
			"shipping_applicable" : false,
			"estimated_delivery_on" : 1396310400,
			"project_id" : 1982976381,
			"remaining" : 50,
			"backers_count" : 0,
			"updated_at" : 1363809906
		},
		{
			"id" : 1459232,
			"minimum" : 1000,
			"reward" : "Cradle of life Edition:\\r\\n\\r\\ncrammed with everything from the tier above with the additional bonus of receiving your own customized drawn African mask, with a short description added to explain the psychology behind it AND your name printed on the back of the t-shirt as a Muti supporter.",
			"limit" : 25,
			"shipping_applicable" : false,
			"estimated_delivery_on" : 1396310400,
			"project_id" : 1982976381,
			"remaining" : 25,
			"backers_count" : 0,
			"updated_at" : 1363874845
		},
		{
			"id" : 1459233,
			"minimum" : 5000,
			"reward" : "Ancestry Edition:\\r\\n\\r\\nThis is our highest tier it carries everything every tier has had to offer up to now, including a print of your choice from the selected original art, a digitally drawn mask and now with the added feature of having your mask built in game for Zola to find and collect. Etched on the back, your name and a customized thanks from the whole Muti team.",
			"limit" : 15,
			"shipping_applicable" : false,
			"estimated_delivery_on" : 1396310400,
			"project_id" : 1982976381,
			"remaining" : 15,
			"backers_count" : 0,
			"updated_at" : 1363809906
		}
	]
}